[
  {
    "id": "440921",
    "name": "Compile: Aux 2",
    "rating": 0.0,
    "avgweight": 0.0,
    "minplayers": 2,
    "maxplayers": 2,
    "playingtime": 30,
    "yearpublished": "2025",
    "average": 9.0,
    "itemtype": "expansion",
    "bggbestplayers": "",
    "bggrecplayers": ""
  },
  {
    "id": "440606",
    "name": "Compile: Main 2",
    "rating": 0.0,
    "avgweight": 0.0,
    "minplayers": 2,
    "maxplayers": 2,
    "playingtime": 30,
    "yearpublished": "2025",
    "average": 8.52537,
    "itemtype": "standalone",
    "bggbestplayers": "2",
    "bggrecplayers": "2"
  },
  {
    "id": "420033",
    "name": "Vantage",
    "rating": 0.0,
    "avgweight": 2.3352,
    "minplayers": 1,
    "maxplayers": 6,
    "playingtime": 180,
    "yearpublished": "2025",
    "average": 8.45887,
    "itemtype": "standalone",
    "bggbestplayers": "2",
    "bggrecplayers": "1,2,3"
  },
  {
    "id": "421689",
    "name": "Expeditions: Gears of Corruption",
    "rating": 0.0,
    "avgweight": 3.2632,
    "minplayers": 1,
    "maxplayers": 6,
    "playingtime": 90,
    "yearpublished": "2024",
    "average": 8.35037,
    "itemtype": "expansion",
    "bggbestplayers": "3",
    "bggrecplayers": "1,2,3,4"
  },
  {
    "id": "256916",
    "name": "Concordia Venus",
    "rating": 0.0,
    "avgweight": 2.9953,
    "minplayers": 2,
    "maxplayers": 6,
    "playingtime": 120,
    "yearpublished": "2018",
    "average": 8.26001,
    "itemtype": "standalone",
    "bggbestplayers": "4",
    "bggrecplayers": "2,3,4,5,6"
  },
  {
    "id": "417813",
    "name": "Compile: Aux  1",
    "rating": 0.0,
    "avgweight": 2.0,
    "minplayers": 2,
    "maxplayers": 2,
    "playingtime": 30,
    "yearpublished": "2024",
    "average": 8.17408,
    "itemtype": "expansion",
    "bggbestplayers": "",
    "bggrecplayers": ""
  },
  {
    "id": "380109",
    "name": "\u30a8\u30b9\u30da\u30e9\u30a4\u30bc\u30fc\u30b7\u30e7\u30f3 (Gibberers: The Word Game of Language Invention and Civilization Development)",
    "rating": 0.0,
    "avgweight": 2.6667,
    "minplayers": 3,
    "maxplayers": 5,
    "playingtime": 180,
    "yearpublished": "2024",
    "average": 8.07524,
    "itemtype": "standalone",
    "bggbestplayers": "4,5",
    "bggrecplayers": "2,3,4,5"
  },
  {
    "id": "400498",
    "name": "Light Speed: Arena",
    "rating": 0.0,
    "avgweight": 1.1,
    "minplayers": 1,
    "maxplayers": 4,
    "playingtime": 15,
    "yearpublished": "2025",
    "average": 8.06097,
    "itemtype": "standalone",
    "bggbestplayers": "4",
    "bggrecplayers": "1,2,3,4"
  },
  {
    "id": "406652",
    "name": "Compile: Main 1",
    "rating": 0.0,
    "avgweight": 2.3095,
    "minplayers": 2,
    "maxplayers": 2,
    "playingtime": 30,
    "yearpublished": "2024",
    "average": 7.91236,
    "itemtype": "standalone",
    "bggbestplayers": "2",
    "bggrecplayers": "2"
  },
  {
    "id": "434906",
    "name": "Tag Team",
    "rating": 0.0,
    "avgweight": 1.96,
    "minplayers": 2,
    "maxplayers": 2,
    "playingtime": 10,
    "yearpublished": "2025",
    "average": 7.9044,
    "itemtype": "standalone",
    "bggbestplayers": "2",
    "bggrecplayers": "2"
  },
  {
    "id": "446699",
    "name": "ANTS",
    "rating": 0.0,
    "avgweight": 3.9091,
    "minplayers": 2,
    "maxplayers": 4,
    "playingtime": 90,
    "yearpublished": "2025",
    "average": 7.88941,
    "itemtype": "standalone",
    "bggbestplayers": "3,4",
    "bggrecplayers": "2,3,4"
  },
  {
    "id": "300322",
    "name": "Hallertau",
    "rating": 0.0,
    "avgweight": 3.2943,
    "minplayers": 1,
    "maxplayers": 4,
    "playingtime": 140,
    "yearpublished": "2020",
    "average": 7.83436,
    "itemtype": "standalone",
    "bggbestplayers": "2",
    "bggrecplayers": "1,2,3,4"
  },
  {
    "id": "403217",
    "name": "7 Wonders: Architects \u2013 Medals",
    "rating": 0.0,
    "avgweight": 1.4167,
    "minplayers": 2,
    "maxplayers": 7,
    "playingtime": 25,
    "yearpublished": "2024",
    "average": 7.78505,
    "itemtype": "expansion",
    "bggbestplayers": "4,5,6",
    "bggrecplayers": "2,3,4,5,6,7"
  },
  {
    "id": "422780",
    "name": "Mistborn: The Deckbuilding Game",
    "rating": 0.0,
    "avgweight": 2.6667,
    "minplayers": 1,
    "maxplayers": 4,
    "playingtime": 60,
    "yearpublished": "2024",
    "average": 7.7427,
    "itemtype": "standalone",
    "bggbestplayers": "2",
    "bggrecplayers": "1,2,3,4"
  },
  {
    "id": "429661",
    "name": "Tofu Shifu",
    "rating": 0.0,
    "avgweight": 2.75,
    "minplayers": 2,
    "maxplayers": 4,
    "playingtime": 90,
    "yearpublished": "2024",
    "average": 7.56759,
    "itemtype": "standalone",
    "bggbestplayers": "3,4",
    "bggrecplayers": "2,3,4"
  },
  {
    "id": "402111",
    "name": "Kronologic: Paris 1920",
    "rating": 0.0,
    "avgweight": 2.1163,
    "minplayers": 1,
    "maxplayers": 4,
    "playingtime": 30,
    "yearpublished": "2024",
    "average": 7.53284,
    "itemtype": "standalone",
    "bggbestplayers": "1,3",
    "bggrecplayers": "1,2,3,4"
  },
  {
    "id": "329873",
    "name": "Grove: 9 card solitaire game",
    "rating": 0.0,
    "avgweight": 1.3103,
    "minplayers": 1,
    "maxplayers": 1,
    "playingtime": 10,
    "yearpublished": "2021",
    "average": 7.53259,
    "itemtype": "standalone",
    "bggbestplayers": "1",
    "bggrecplayers": "1"
  },
  {
    "id": "284217",
    "name": "Rush M.D.",
    "rating": 0.0,
    "avgweight": 2.3667,
    "minplayers": 1,
    "maxplayers": 4,
    "playingtime": 45,
    "yearpublished": "2020",
    "average": 7.42786,
    "itemtype": "standalone",
    "bggbestplayers": "3",
    "bggrecplayers": "2,3,4"
  },
  {
    "id": "371183",
    "name": "JOYRIDE: Survival of the Fastest",
    "rating": 0.0,
    "avgweight": 2.2381,
    "minplayers": 2,
    "maxplayers": 4,
    "playingtime": 60,
    "yearpublished": "2024",
    "average": 7.30735,
    "itemtype": "standalone",
    "bggbestplayers": "3,4",
    "bggrecplayers": "2,3,4"
  },
  {
    "id": "156496",
    "name": "March of the Ants",
    "rating": 0.0,
    "avgweight": 2.716,
    "minplayers": 1,
    "maxplayers": 5,
    "playingtime": 90,
    "yearpublished": "2015",
    "average": 7.12283,
    "itemtype": "standalone",
    "bggbestplayers": "3,4",
    "bggrecplayers": "1,2,3,4,5"
  },
  {
    "id": "367201",
    "name": "Taiwan Night Market",
    "rating": 0.0,
    "avgweight": 2.4545,
    "minplayers": 2,
    "maxplayers": 5,
    "playingtime": 80,
    "yearpublished": "2023",
    "average": 7.0102,
    "itemtype": "standalone",
    "bggbestplayers": "4",
    "bggrecplayers": "3,4,5"
  },
  {
    "id": "315043",
    "name": "Scape Goat",
    "rating": 0.0,
    "avgweight": 1.65,
    "minplayers": 3,
    "maxplayers": 6,
    "playingtime": 30,
    "yearpublished": "2020",
    "average": 6.93527,
    "itemtype": "standalone",
    "bggbestplayers": "4,5",
    "bggrecplayers": "4,5,6"
  },
  {
    "id": "435759",
    "name": "Beaver House",
    "rating": 0.0,
    "avgweight": 1.0,
    "minplayers": 2,
    "maxplayers": 4,
    "playingtime": 20,
    "yearpublished": "2025",
    "average": 6.85,
    "itemtype": "standalone",
    "bggbestplayers": "",
    "bggrecplayers": ""
  },
  {
    "id": "42487",
    "name": "Lost Cities: The Board Game",
    "rating": 0.0,
    "avgweight": 1.7268,
    "minplayers": 2,
    "maxplayers": 4,
    "playingtime": 60,
    "yearpublished": "2008",
    "average": 6.79914,
    "itemtype": "standalone",
    "bggbestplayers": "3,4",
    "bggrecplayers": "2,3,4"
  },
  {
    "id": "452411",
    "name": "Giants Moving Tiny Furniture",
    "rating": 0.0,
    "avgweight": 0.0,
    "minplayers": 3,
    "maxplayers": 8,
    "playingtime": 10,
    "yearpublished": "2025",
    "average": 6.66667,
    "itemtype": "standalone",
    "bggbestplayers": "",
    "bggrecplayers": ""
  }
]